PyQt6_SwitchControl/PyQt6_SwitchControl.py
PyQt6_SwitchControl/PyQt6_SwitchControl_plugin.py
PyQt6_SwitchControl/__init__.py
PyQt6_SwitchControl/__main__.py
PyQt6_SwitchControl-1.0.4.post1.dist-info/LICENSE
PyQt6_SwitchControl-1.0.4.post1.dist-info/METADATA
PyQt6_SwitchControl-1.0.4.post1.dist-info/WHEEL
PyQt6_SwitchControl-1.0.4.post1.dist-info/entry_points.txt
PyQt6_SwitchControl-1.0.4.post1.dist-info/top_level.txt
PyQt6_SwitchControl-1.0.4.post1.dist-info/RECORD
