Metadata-Version: 2.1
Name: PyQt6_SwitchControl
Version: 1.0.4.post1
Summary: An easy-to-use and modern toggle switch for Qt Python binding PyQt
Home-page: https://github.com/M1GW/PyQt6_SwitchControl
Author: Parsa.py
Author-email: "Parsa.py" <munichbayern2005@gmail.com>
Maintainer: M1GW
License: LICENSE
Project-URL: Repository, https://github.com/M1GW/PyQt6_SwitchControl
Project-URL: Issues, https://github.com/M1GW/PyQt6_SwitchControl/issues
Keywords: PyQt,PyQt6,switch,toggle,toggle-button,toggle-switch,qt6-widgets,qt
Classifier: Programming Language :: Python :: 3
Classifier: Programming Language :: Python :: 3.8
Classifier: Programming Language :: Python :: 3.9
Classifier: Programming Language :: Python :: 3.10
Classifier: Programming Language :: Python :: 3.11
Classifier: Programming Language :: Python :: 3.12
Classifier: Programming Language :: Python :: Implementation :: CPython
Classifier: License :: OSI Approved :: MIT License
Requires-Python: >=3.8
License-File: LICENSE
Requires-Dist: PyQt6
